xiaoaitts/__init__.py
xiaoaitts/const.py
xiaoaitts/get_device.py
xiaoaitts/login.py
xiaoaitts/nlp.py
xiaoaitts/tts.py
xiaoaitts/lib/__init__.py
xiaoaitts/lib/error.py
xiaoaitts/lib/invoke.py
xiaoaitts/lib/request.py
xiaoaitts/miot/__init__.py
xiaoaitts/miot/get_device.py
xiaoaitts/miot/get_device_spec.py
xiaoaitts/player/__init__.py
xiaoaitts/player/get_context.py
xiaoaitts/player/get_playlist.py
xiaoaitts/player/get_playlist_songs.py
xiaoaitts/player/get_song_info.py
xiaoaitts/player/get_status.py
xiaoaitts/player/get_volume.py
xiaoaitts/player/next.py
xiaoaitts/player/pause.py
xiaoaitts/player/play.py
xiaoaitts/player/play_album_playlist.py
xiaoaitts/player/play_url.py
xiaoaitts/player/prev.py
xiaoaitts/player/set_play_loop.py
xiaoaitts/player/set_volume.py
xiaoaitts/player/toggle_play_state.py
xiaoaitts-0.1.1.dist-info/LICENSE
xiaoaitts-0.1.1.dist-info/METADATA
xiaoaitts-0.1.1.dist-info/WHEEL
xiaoaitts-0.1.1.dist-info/top_level.txt
xiaoaitts-0.1.1.dist-info/RECORD
