Metadata-Version: 2.1
Name: xiaoaitts
Version: 0.1.1
Summary: 小爱音箱自定义文本朗读
Home-page: https://github.com/cnmax/xiaoaitts
Author: Max
Author-email: mr.qchao@gmail.com
Project-URL: Bug Tracker, https://github.com/cnmax/xiaoaitts/issues
Classifier: Programming Language :: Python :: 3
Classifier: License :: OSI Approved :: MIT License
Classifier: Operating System :: OS Independent
Requires-Python: >=3.6
License-File: LICENSE
Requires-Dist: requests
